odoo/addons/sales_team_security/README.rst
odoo/addons/sales_team_security/__init__.py
odoo/addons/sales_team_security/__manifest__.py
odoo/addons/sales_team_security/hooks.py
odoo/addons/sales_team_security/i18n/es.po
odoo/addons/sales_team_security/i18n/it.po
odoo/addons/sales_team_security/i18n/pt.po
odoo/addons/sales_team_security/i18n/sales_team_security.pot
odoo/addons/sales_team_security/i18n/tr.po
odoo/addons/sales_team_security/models/__init__.py
odoo/addons/sales_team_security/models/ir_rule.py
odoo/addons/sales_team_security/models/res_partner.py
odoo/addons/sales_team_security/readme/CONFIGURE.md
odoo/addons/sales_team_security/readme/CONTRIBUTORS.md
odoo/addons/sales_team_security/readme/DESCRIPTION.md
odoo/addons/sales_team_security/readme/INSTALL.md
odoo/addons/sales_team_security/readme/ROADMAP.md
odoo/addons/sales_team_security/security/sales_team_security.xml
odoo/addons/sales_team_security/static/description/icon.png
odoo/addons/sales_team_security/static/description/index.html
odoo/addons/sales_team_security/tests/__init__.py
odoo/addons/sales_team_security/tests/common.py
odoo/addons/sales_team_security/tests/test_sales_team_security.py
odoo_addon_sales_team_security-18.0.1.0.0.4.dist-info/METADATA
odoo_addon_sales_team_security-18.0.1.0.0.4.dist-info/WHEEL
odoo_addon_sales_team_security-18.0.1.0.0.4.dist-info/top_level.txt
odoo_addon_sales_team_security-18.0.1.0.0.4.dist-info/RECORD
